{
  "type": "flash",
  "date": "2026-03-24",
  "generated_at": "2026-03-24T20:00:41.548896+00:00",
  "post_id": "116285908636437489",
  "post_content": "It is my Great Honor to endorse State Representative Michelle Davis, a REAL Republican running for Indiana's 41st State Senate District (which I won by 33 points!), against RINO incumbent Greg Walker!",
  "signals": "",
  "direction": "NEUTRAL",
  "confidence": 0.0,
  "articles": {
    "zh": {
      "status": "ok",
      "path": "/Users/tkman/Projects/trump-code/articles/2026-03/24-flash-2000-zh.md",
      "length": 447
    },
    "en": {
      "status": "ok",
      "path": "/Users/tkman/Projects/trump-code/articles/2026-03/24-flash-2000-en.md",
      "length": 1506
    },
    "ja": {
      "status": "ok",
      "path": "/Users/tkman/Projects/trump-code/articles/2026-03/24-flash-2000-ja.md",
      "length": 463
    }
  }
}